kong_gateway_client/__init__.py
kong_gateway_client/api.py
kong_gateway_client/client.py
kong_gateway_client/common.py
kong_gateway_client/resources/__init__.py
kong_gateway_client/resources/consumer_groups.py
kong_gateway_client/resources/consumers.py
kong_gateway_client/resources/plugin_types/__init__.py
kong_gateway_client/resources/plugin_types/acl.py
kong_gateway_client/resources/plugin_types/key_auth.py
kong_gateway_client/resources/plugin_types/rate_limiting_advanced.py
kong_gateway_client/resources/plugins.py
kong_gateway_client/resources/routes.py
kong_gateway_client/resources/services.py
kong_gateway_client/resources/workspaces.py
kong_gateway_client/utils/helpers.py
kong_gateway_client-0.6.0.dist-info/METADATA
kong_gateway_client-0.6.0.dist-info/WHEEL
kong_gateway_client-0.6.0.dist-info/RECORD
