Metadata-Version: 2.1
Name: kong-gateway-client
Version: 0.6.0
Summary: A limited client for the Kong Gateway admin API
Author: Steve Brown
Author-email: stephen.brown@konghq.com
Requires-Python: >=3.9,<4.0
Classifier: Programming Language :: Python :: 3
Classifier: Programming Language :: Python :: 3.9
Classifier: Programming Language :: Python :: 3.10
Classifier: Programming Language :: Python :: 3.11
Requires-Dist: requests (==2.31.0)
Requires-Dist: urllib3 (==2.0.5)
